mynewthing/__init__.py
mynewthing/cli.py
mynewthing-0.1.0.dist-info/METADATA
mynewthing-0.1.0.dist-info/WHEEL
mynewthing-0.1.0.dist-info/entry_points.txt
mynewthing-0.1.0.dist-info/RECORD
