Metadata-Version: 2.3
Name: mynewthing
Version: 0.1.0
Summary: 
Author: Rodney Martin
Author-email: rodney.martin@saultcollege.ca
Requires-Python: >=3.12
Classifier: Programming Language :: Python :: 3
Classifier: Programming Language :: Python :: 3.12
Classifier: Programming Language :: Python :: 3.13
Requires-Dist: rich (>=14.0.0,<15.0.0)
